flaky/__init__.py
flaky/_flaky_plugin.py
flaky/defaults.py
flaky/flaky_decorator.py
flaky/flaky_nose_plugin.py
flaky/flaky_pytest_plugin.py
flaky/multiprocess_string_io.py
flaky/names.py
flaky/utils.py
flaky-3.6.1.dist-info/AUTHORS.rst
flaky-3.6.1.dist-info/LICENSE
flaky-3.6.1.dist-info/METADATA
flaky-3.6.1.dist-info/WHEEL
flaky-3.6.1.dist-info/entry_points.txt
flaky-3.6.1.dist-info/top_level.txt
flaky-3.6.1.dist-info/RECORD
